{
  "animals": [
    {
      "id": 1,
      "name": "Peggy",
      "breed": "Pug",
      "customerId": 1,
      "locationId": 2
    },
    {
      "id": 2,
      "name": "Snippet",
      "breed": "Daschund",
      "customerId": 2,
      "locationId": 3
    },
    {
      "id": 3,
      "name": "Burrito",
      "breed": "Bulldog",
      "customerId": 3,
      "locationId": 4
    },
    {
      "id": 4,
      "name": "Bark",
      "breed": "Golden Retriever",
      "customerId": 4,
      "locationId": 5
    },
    {
      "id": 5,
      "name": "Gif",
      "breed": "Labador",
      "customerId": 5,
      "locationId": 6
    },
    {
      "id": 6,
      "name": "Bixo do Coco",
      "breed": "Chihuahua",
      "customerId": 1,
      "locationId": 2
    },
    {
      "name": "Pal",
      "breed": "Vicious teddy bear killer",
      "locationId": 3,
      "customerId": 2,
      "id": 7
    },
    {
      "name": "Nook",
      "breed": "Huskey",
      "locationId": 5,
      "customerId": 5,
      "id": 8
    }
  ],
  "customers": [
    {
      "id": 7,
      "name": "Hannah Hall",
      "address": "7002 Chestnut Ct",
      "email": "hannah.hall@gmail.com"
    },
    {
      "id": 1,
      "name": "Customer 1",
      "address": "123 W Fake St",
      "email": "customer1@gmail.com"
    },
    {
      "id": 2,
      "name": "Customer 2",
      "address": "456 Also Fake Rd.",
      "email": "customer2@gmail.com"
    },
    {
      "id": 3,
      "name": "Customer 3",
      "address": "789 Fake Way",
      "email": "customer3@gmail.com"
    },
    {
      "id": 4,
      "name": "Customer 4",
      "address": "1234 Fake Blvd",
      "email": "customer4@gmail.com"
    },
    {
      "id": 5,
      "name": "Customer 5",
      "address": "5678 Fake Ct",
      "email": "customer5@gmail.com"
    },
    {
      "id": 6,
      "name": "Customer 6",
      "address": "123 E Fake St",
      "email": "customer6@gmail.com"
    },
    {
      "email": "test.name@gmail.com",
      "name": "test name",
      "id": 8
    }
  ],
  "employees": [
    {
      "id": 1,
      "name": "Peggy",
      "job": "Professional Dog Snuggles",
      "locationId": 1
    },
    {
      "id": 2,
      "name": "Cat Lady",
      "job": "Picks up cat poop",
      "locationId": 1
    },
    {
      "id": 3,
      "name": "Mage",
      "job": "Eats poop",
      "locationId": 2
    },
    {
      "id": 4,
      "name": "Hobo Jack",
      "job": "Doesn't actually work here, just hangs out here.",
      "locationId": 2
    },
    {
      "id": 5,
      "name": "Drifter Jeff",
      "job": "Hobo Jack's friend",
      "locationId": 3
    },
    {
      "id": 6,
      "name": "Charlie",
      "job": "Horse without a liver.",
      "locationId": 3
    },
    {
      "name": "Sunny",
      "job": "Ray Of Happiness",
      "locationId": 2,
      "id": 7
    }
  ],
  "locations": [
    {
      "id": 1,
      "name": "Nashville North",
      "address": "8422 E Johnson Pike"
    },
    {
      "id": 2,
      "name": "Nashville South",
      "address": "209 W Emory Drive"
    },
    {
      "id": 3,
      "name": "Nashville East",
      "address": "8422 N Johnson Pike"
    },
    {
      "id": 4,
      "name": "Nashville West",
      "address": "209 S Emory Drive"
    },
    {
      "id": 5,
      "name": "Nashville North",
      "address": "8422 N Johnson Pike"
    },
    {
      "id": 6,
      "name": "Nashville South",
      "address": "209 S Emory Drive"
    },
    {
      "name": "testloc1",
      "address": "123 fake street, nashville tn",
      "id": 7
    }
  ]
}